zvideo/__init__.py
zvideo-0.1.0.dist-info/METADATA
zvideo-0.1.0.dist-info/WHEEL
zvideo-0.1.0.dist-info/licenses/LICENSE
zvideo-0.1.0.dist-info/RECORD
