Metadata-Version: 2.1
Name: zvideo
Version: 0.1.0
Summary: zen video library
Project-URL: Homepage, https://github.com/inspirare6/zvideo
Project-URL: Bug Tracker, https://github.com/inspirare6/zvideo/issues
Author-email: inspirare6 <inspirare6@163.com>
License-File: LICENSE
Classifier: License :: OSI Approved :: MIT License
Classifier: Operating System :: OS Independent
Classifier: Programming Language :: Python :: 3
Requires-Python: >=3.7
